{
  "custom": {
    "groups": [
      "schoelkopf"
    ]
  },
  "zotero": {
    "abstractNote": "Background: The COVID-19 pandemic has triggered a surge in the development of clinical predictive models for the diagnosis and prognosis of patients with COVID-19. However, the quality and clinical utility of these models remain unclear. Objective: This study aims to systematically review and evaluate the clinical predictive models developed for COVID-19 to provide a comprehensive overview of the current state of the field and identify potential pitfalls in model development. Methods: We performed a systematic search of the literature for clinical predictive models for COVID-19 published between January 1, 2020, and May 15, 2020. We extracted information on the study design, model development, and validation procedures. We assessed the risk of bias and the applicability of the models using the Prediction Model Risk of Bias Assessment Tool (PROBAST). Results: We identified 22 studies describing 31 predictive models. Most models were developed using small, nonrepresentative datasets and lacked external validation. The majority of models were at high risk of bias, primarily due to inappropriate exclusion of patients, lack of blinding, and overfitting. Conclusions: The current landscape of clinical predictive models for COVID-19 is characterized by a high risk of bias and limited clinical utility. Future research should prioritize the use of large, representative datasets, rigorous validation procedures, and transparent reporting to ensure the development of reliable and clinically useful models.",
    "extra": {
      "Source": "group_webpage (schoelkopf)"
    },
    "itemType": "journalArticle"
  }
}
