{
  "custom": {
    "groups": [
      "williamson"
    ],
    "mentions_ai_center": true
  },
  "zotero": {
    "attachments": [
      {
        "accessDate": "2025-06-17 16:15:45",
        "linkMode": "3",
        "mimeType": "application/pdf",
        "path": null,
        "title": "Full Text PDF",
        "url": "https://www.degruyterbrill.com/document/doi/10.1515/jci-2023-0001/pdf?licenseType=open-access"
      }
    ],
    "notes": [
      {
        "note": "<p>num_citations: 2025-07-31 : 0</p>",
        "relations": null,
        "tags": null
      },
      {
        "note": "<p>”num_citations”: ”2025-05-31”: 0</p>",
        "relations": null,
        "tags": null
      },
      {
        "note": "<p>Publisher: University of Tübingen</p>",
        "relations": null,
        "tags": null
      }
    ]
  }
}
