{
  "custom": {
    "groups": [
      "orvieto"
    ]
  },
  "zotero": {
    "abstractNote": "Continual learning aims to learn a sequence of tasks without forgetting previously acquired knowledge. A central challenge is the stability-plasticity trade-off: the model must be stable enough to retain old knowledge while being plastic enough to learn new tasks. In this paper, we propose a novel approach to address this trade-off by introducing auxiliary networks. Our method leverages these auxiliary networks to selectively update the main model's parameters, effectively balancing stability and plasticity. We demonstrate the effectiveness of our approach through extensive experiments on standard continual learning benchmarks, showing that it consistently outperforms existing methods.",
    "archive": "arXiv",
    "archiveLocation": "arXiv:2303.09483",
    "extra": {
      "Archive ID": "2303.09483",
      "Citations@2026-06-01": "2",
      "OpenAlex": "W4327811198",
      "Repository": "arXiv",
      "Scholar": "xkuLyHoAAAAJ:M3ejUd6NZC8C"
    },
    "itemType": "document",
    "libraryCatalog": "arXiv"
  }
}
