{
  "custom": {
    "groups": [
      "schoelkopf"
    ]
  },
  "zotero": {
    "abstractNote": "Machine teaching aims to find the optimal training set to make a learner converge to a target model as quickly as possible. Existing teaching methods often assume that the teacher can select examples from a fixed pool or synthesize examples from the input space. However, in many real-world scenarios, the teacher may only be able to provide labels for a fixed set of inputs. In this paper, we propose Iterative Teaching by Label Synthesis (ITLS), a novel teaching framework that allows the teacher to synthesize labels for a fixed set of inputs to guide the learner. We formulate ITLS as a bilevel optimization problem and solve it by alternating between updating the learner's parameters and optimizing the synthesized labels. We show that ITLS can be interpreted as a form of iterative teaching, where the teacher iteratively refines the labels to improve the learner's performance. We demonstrate the effectiveness of ITLS on various machine learning tasks, including image classification and robust learning, and show that it outperforms existing teaching methods.",
    "extra": {
      "Citations@2026-06-01": "1",
      "OpenAlex": "W3208320400",
      "Pages": "21681--21695",
      "Scholar": "DZ-fHPgAAAAJ:91mu7JjQo40C"
    },
    "itemType": "document"
  }
}
