{
  "custom": {
    "groups": [
      "bethge"
    ]
  },
  "zotero": {
    "abstractNote": "Henderson et al. (2021) argue that meaning maps—a computational model of semantic content in scenes—predict gaze guidance independently of low-level image features. We re-evaluate their evidence and show that their conclusions are not supported by their data. Specifically, we demonstrate that the meaning maps used by Henderson et al. are highly correlated with low-level image features, and that once these features are controlled for, the meaning maps explain no additional variance in gaze guidance. We conclude that there is currently no evidence that meaning maps capture semantic information relevant to gaze guidance.",
    "extra": {
      "Citations@2026-06-01": "7",
      "OpenAlex": "W3157638712",
      "Publication Title": "Cognition 214, 104741, 2021",
      "Scholar": "0z0fNxUAAAAJ:kzcSZmkxUKAC"
    },
    "itemType": "document"
  }
}
