{
  "custom": {
    "groups": [
      "hennig",
      "schoelkopf"
    ]
  },
  "zotero": {
    "abstractNote": "Bayesian quadrature (BQ) is a framework for numerical integration that treats the integral as a latent value to be inferred. While BQ is often used with adaptive designs to select evaluation points, theoretical guarantees for such adaptive methods are limited. This paper provides convergence guarantees for adaptive BQ methods. We show that, under mild conditions on the integrand and the kernel, the BQ posterior mean converges to the true integral value at a rate determined by the fill distance of the design points. We also provide a convergence rate for the BQ posterior variance, which serves as a measure of uncertainty. Our results cover a wide range of adaptive strategies, including those based on the BQ posterior variance and those based on information-theoretic criteria.",
    "conferenceName": "Advances in Neural Information Processing Systems 32 (NeurIPS 2019)",
    "extra": {
      "Citations@2026-06-01": "13",
      "Event Place": "Vancouver, Canada",
      "OpenAlex": "W2944890416",
      "Scholar": "UeG5w08AAAAJ:SP6oXDckpogC",
      "Source": "group_webpage (schoelkopf)"
    },
    "itemType": "conferencePaper",
    "proceedingsTitle": "Advances in Neural Information Processing Systems 32"
  }
}
